fire/__init__.py
fire/cook.py
fire/defence.py
fire/sticks.png
python_fire-0.1.0.dist-info/DESCRIPTION.rst
python_fire-0.1.0.dist-info/METADATA
python_fire-0.1.0.dist-info/metadata.json
python_fire-0.1.0.dist-info/RECORD
python_fire-0.1.0.dist-info/top_level.txt
python_fire-0.1.0.dist-info/WHEEL
