Metadata-Version: 2.0
Name: python-fire
Version: 0.1.0
Summary: FIRE HOT. TREE PRETTY
Home-page: https://github.com/grub/python-fire
Author: Grug
Author-email: grug@example.com
License: MIT
Keywords: fire cook dinosaur protection
Platform: UNKNOWN
Classifier: Development Status :: 3 - Alpha
Classifier: Intended Audience :: Developers
Classifier: Topic :: Software Development :: Build Tools
Classifier: License :: OSI Approved :: MIT License
Classifier: Programming Language :: Python :: 2
Classifier: Programming Language :: Python :: 2.6
Classifier: Programming Language :: Python :: 2.7
Classifier: Programming Language :: Python :: 3
Classifier: Programming Language :: Python :: 3.2
Classifier: Programming Language :: Python :: 3.3
Classifier: Programming Language :: Python :: 3.4
Requires-Dist: pygments
